[
    {
        "name": "Swamp",
        "access_rules": [
            "@Swamp Access"
        ],
        "children": [
            {
                "name": "rA1_98",
                "sections": [
                    {
                        "ref": "Skills/Armor"
                    }
                ],
                "map_locations": [
                    {
                        "map": "Swamp",
                        "x": "0",
                        "y": "0"
                    }
                ]
            },
            {
                "name": "rA1_97",
                "sections": [
                    {
                        "ref": "Talismans/Throws"
                    }
                ],
                "map_locations": [
                    {
                        "map": "Swamp",
                        "x": "0",
                        "y": "0"
                    }
                ]
            },
            {
                "name": "rA1_96",
                "sections": [
                    {
                        "ref": "Checkpoints/Green Area Entry"
                    }
                ],
                "map_locations": [
                    {
                        "map": "Swamp",
                        "x": "0",
                        "y": "0"
                    }
                ]
            },
            {
                "name": "Armor Area",
                "access_rules": [
                    "@Armor Area Access"
                ],
                "children": [
                    {
                        "name": "rA1_112",
                        "sections": [
                            {
                                "ref": "Shards/Yellow Shard"
                            }
                        ],
                        "map_locations": [
                            {
                                "map": "Swamp",
                                "x": "0",
                                "y": "0"
                            }
                        ]
                    },
                    {
                        "name": "rA1_100Coin",
                        "sections": [
                            {
                                "ref": "Coins/Armor Time Puzzle"
                            }
                        ],
                        "map_locations": [
                            {
                                "map": "Swamp",
                                "x": "0",
                                "y": "0"
                            }
                        ]
                    },
                    {
                        "name": "rA1_105",
                        "sections": [
                            {
                                "ref": "Coins/Father"
                            }
                        ],
                        "map_locations": [
                            {
                                "map": "Swamp",
                                "x": "0",
                                "y": "0"
                            }
                        ]
                    },
                    {
                        "name": "rA1_102",
                        "sections": [
                            {
                                "ref": "Talismans/Warps"
                            }
                        ],
                        "map_locations": [
                            {
                                "map": "Swamp",
                                "x": "0",
                                "y": "0"
                            }
                        ]
                    },
                    {
                        "name": "rA1_103CP",
                        "sections": [
                            {
                                "ref": "Checkpoints/Father"
                            }
                        ],
                        "map_locations": [
                            {
                                "map": "Swamp",
                                "x": "0",
                                "y": "0"
                            }
                        ]
                    },
                    {
                        "name": "rA1_109",
                        "sections": [
                            {
                                "ref": "Checkpoints/Deceiver"
                            }
                        ],
                        "map_locations": [
                            {
                                "map": "Swamp",
                                "x": "0",
                                "y": "0"
                            }
                        ]
                    }
                ]
            }
        ]
    }
]