[
    {
        "name": "Blossom - Overworld",
        "children": [
            {
                "sections": [
                    {
                        "ref": "Blossom/rA0_4PowerUp/Dodge"
                    }
                ],
                "map_locations": [
                    {
                        "map": "Overworld",
                        "x": "810",
                        "y": "491"
                    }
                ]
            },
            {
                "sections": [
                    {
                        "ref": "Blossom/rA1_136Love/Love Room"
                    }
                ],
                "map_locations": [
                    {
                        "map": "Overworld",
                        "x": "0",
                        "y": "0"
                    }
                ]
            },
            {
                "sections": [
                    {
                        "ref": "Blossom/rA0_5Coin/Rogue"
                    }
                ],
                "map_locations": [
                    {
                        "map": "Overworld",
                        "x": "0",
                        "y": "0"
                    }
                ]
            },
            {
                "sections": [
                    {
                        "ref": "Blossom/rA0_0/Start Room"
                    }
                ],
                "map_locations": [
                    {
                        "map": "Overworld",
                        "x": "0",
                        "y": "0"
                    }
                ]
            },
            {
                "sections": [
                    {
                        "ref": "Blossom/rA1_0runway/Runway"
                    }
                ],
                
                "map_locations": [
                    {
                        "map": "Overworld",
                        "x": "0",
                        "y": "0"
                    }
                ]
            },
            {
                "sections": [
                    {
                        "ref": "Blossom/rA0_4/Rogue"
                    }
                ],
                
                "map_locations": [
                    {
                        "map": "Overworld",
                        "x": "0",
                        "y": "0"
                    }
                ]
            }
        ]
    },
    {
        "name": "Crystal Break Area - Overworld",
        "children": [
            {
                "sections": [
                    {
                        "ref": "Blossom/Crystal Break Area/rA1_8/Crystal Break"
                    }
                ],
                "map_locations": [
                    {
                        "map": "Overworld",
                        "x": "483",
                        "y": "492"
                    }
                ]
            },
            {
                "sections": [
                    {
                        "ref": "Blossom/Crystal Break Area/rA1_8Basement/Basement"
                    }
                ],
                "map_locations": [
                    {
                        "map": "Overworld",
                        "x": "0",
                        "y": "0"
                    }
                ]
            }
        ]
    },
    {
        "name": "Blossom Middle - Overworld",
        "children": [
            {
                "sections": [
                    {
                        "ref": "Blossom/Blossom Middle/rA1_1under/Under Leaves"
                    }
                ],
                "map_locations": [
                    {
                        "map": "Overworld",
                        "x": "0",
                        "y": "0"
                    }
                ]
            }
        ]
    },
    {
        "name": "Vagrant Area - Overworld",
        "children": [
            {
                "sections": [
                    {
                        "ref": "Blossom/Blossom Middle/Vagrant Area/rA1_1VagrantBossFinalReward/Magic Bar Vagrant"
                    }
                ],
                "map_locations": [
                    {
                        "map": "Overworld",
                        "x": "0",
                        "y": "0"
                    }
                ]
            },
            {
                "sections": [
                    {
                        "ref": "Blossom/Blossom Middle/Vagrant Area/rA1_1Coin0/Hub Left"
                    }
                ],
                "map_locations": [
                    {
                        "map": "Overworld",
                        "x": "0",
                        "y": "0"
                    }
                ]
            },
            {
                "sections": [
                    {
                        "ref": "Blossom/Blossom Middle/Vagrant Area/rA1_1Coin1/Hub Up"
                    }
                ],
                "map_locations": [
                    {
                        "map": "Overworld",
                        "x": "0",
                        "y": "0"
                    }
                ]
            },
            {
                "sections": [
                    {
                        "ref": "Blossom/Blossom Middle/Vagrant Area/rA1_1CP/Vagrant"
                    }
                ],
                "map_locations": [
                    {
                        "map": "Overworld",
                        "x": "0",
                        "y": "0"
                    }
                ]
            }
        ]
    },
    {
        "name": "Bandit Area - Overworld",
        "children": [
            {
                "name": "rA0_4PowerUp",
                "sections": [
                    {
                        "name": "Dodge Upgrade",
                        "ref": "Blossom/Blossom Middle/Bandit Area/rA1_4 - Skill/Dodge Upgrade"
                    }
                ],
                "map_locations": [
                    {
                        "map": "Overworld",
                        "x": "778",
                        "y": "428"
                    }
                ]
            },
            {
                "sections": [
                    {
                        "ref": "Blossom/Blossom Middle/Bandit Area/rA1_4 - Talisman/Bandit"
                    }
                ],
                "map_locations": [
                    {
                        "map": "Overworld",
                        "x": "0",
                        "y": "0"
                    }
                ]
            },
            {
                "sections": [
                    {
                        "ref": "Blossom/Blossom Middle/Bandit Area/rA1_2/Bandit"
                    }
                ],
                "map_locations": [
                    {
                        "map": "Overworld",
                        "x": "0",
                        "y": "0"
                    }
                ]
            }
        ]
    },
    {
        "name": "Blossom Upper - Overworld",
        "children": [
            {
                "sections": [
                    {
                        "ref": "Blossom/Blossom Middle/Blossom Upper/rA1_35 - Rune/Juggernaut Rune"
                    }
                ],
                "map_locations": [
                    {
                        "map": "Overworld",
                        "x": "0",
                        "y": "0"
                    }
                ]
            },
            {
                "sections": [
                    {
                        "ref": "Blossom/Blossom Middle/Blossom Upper/rA1_29VagrantBossReward/Vagrant II Reward"
                    }
                ],
                "map_locations": [
                    {
                        "map": "Overworld",
                        "x": "0",
                        "y": "0"
                    }
                ]
            },
            {
                "sections": [
                    {
                        "ref": "Blossom/Blossom Middle/Blossom Upper/rA1_9/Leave Room"
                    }
                ],
                "map_locations": [
                    {
                        "map": "Overworld",
                        "x": "0",
                        "y": "0"
                    }
                ]
            },
            {
                "sections": [
                    {
                        "ref": "Blossom/Blossom Middle/Blossom Upper/rA1_11Armor/Behind Rocks"
                    }
                ],
                "map_locations": [
                    {
                        "map": "Overworld",
                        "x": "0",
                        "y": "0"
                    }
                ]
            },
            {
                "sections": [
                    {
                        "ref": "Blossom/Blossom Middle/Blossom Upper/rA1_36/Spin Puzzle"
                    }
                ],
                "map_locations": [
                    {
                        "map": "Overworld",
                        "x": "0",
                        "y": "0"
                    }
                ]
            },
            {
                "sections": [
                    {
                        "ref": "Blossom/Blossom Middle/Blossom Upper/rA1_32Deflector/Deflector"
                    }
                ],
                "map_locations": [
                    {
                        "map": "Overworld",
                        "x": "0",
                        "y": "0"
                    }
                ]
            },
            {
                "sections": [
                    {
                        "ref": "Blossom/Blossom Middle/Blossom Upper/rA1_35 - Talisman/Twins"
                    }
                ],
                "map_locations": [
                    {
                        "map": "Overworld",
                        "x": "0",
                        "y": "0"
                    }
                ]
            },
            {
                "sections": [
                    {
                        "ref": "Blossom/Blossom Middle/Blossom Upper/rA1_33/Twins"
                    }
                ],
                "map_locations": [
                    {
                        "map": "Overworld",
                        "x": "0",
                        "y": "0"
                    }
                ]
            }
        ]
    }
]