[
    {
        "name": "Forbidden - Overworld",
        "children": [
            {
                "sections": [
                    {
                        "ref": "Forbidden/rA1_118ArenaFatalReward/Fatal Draw Upgrade"
                    }
                ],
                "map_locations": [
                    {
                        "map": "Overworld",
                        "x": "0",
                        "y": "0"
                    }
                ]
            },
            {
                "sections": [
                    {
                        "ref": "Forbidden/rA1_122/Most Left"
                    }
                ],
                "map_locations": [
                    {
                        "map": "Overworld",
                        "x": "0",
                        "y": "0"
                    }
                ]
            },
            {
                "sections": [
                    {
                        "ref": "Forbidden/rA1_118/Fatal Arena"
                    }
                ],
                "map_locations": [
                    {
                        "map": "Overworld",
                        "x": "0",
                        "y": "0"
                    }
                ]
            }
        ]
    },
    {
        "name": "Forbidden Upper - Overworld",
        "children": [
            {
                "sections": [
                    {
                        "ref": "Forbidden/Forbidden Upper/rA1_134/Demon Blade"
                    }
                ],
                "map_locations": [
                    {
                        "map": "Overworld",
                        "x": "0",
                        "y": "0"
                    }
                ]
            },
            {
                "sections": [
                    {
                        "ref": "Forbidden/Forbidden Upper/rA1_130/Monk"
                    }
                ],
                "map_locations": [
                    {
                        "map": "Overworld",
                        "x": "0",
                        "y": "0"
                    }
                ]
            }
        ]
    }
]